README.md
setup.py
wangyiyunEncrypter/__init__.py
wangyiyunEncrypter/encrypter.py
wangyiyunEncrypter.egg-info/PKG-INFO
wangyiyunEncrypter.egg-info/SOURCES.txt
wangyiyunEncrypter.egg-info/dependency_links.txt
wangyiyunEncrypter.egg-info/top_level.txt