Metadata-Version: 2.1
Name: wangyiyunEncrypter
Version: 0.0.1
Summary: the encrypt functions of 163 music
Home-page: UNKNOWN
Author: flyingdream
Author-email: 1519657825@qq.com
License: UNKNOWN
Platform: UNKNOWN
Classifier: Programming Language :: Python :: 3
Classifier: License :: OSI Approved :: MIT License
Classifier: Operating System :: OS Independent
Requires-Python: >=3.6
